tbongkim03_lotto/__init__.py
tbongkim03_lotto/draw.py
tbongkim03_lotto-0.2.0.dist-info/METADATA
tbongkim03_lotto-0.2.0.dist-info/WHEEL
tbongkim03_lotto-0.2.0.dist-info/top_level.txt
tbongkim03_lotto-0.2.0.dist-info/RECORD
