Metadata-Version: 2.1
Name: tbongkim03_lotto
Version: 0.2.0
Summary: Default template for PDM package
Author-email: tbongkim03 <tbongkim03@gmial.com>
License: MIT
Requires-Python: >=3.9
